Metadata-Version: 2.1
Name: sweet.http
Version: 0.0.3
Summary: Sweet's http autotest module
Home-page: https://github.com/Sweeterio/http
Author: tonglei
Author-email: tonglei@qq.com
License: UNKNOWN
Platform: UNKNOWN
Classifier: Programming Language :: Python :: 3.9
Classifier: License :: OSI Approved :: MIT License
Classifier: Operating System :: OS Independent
